{
  "id": "priceArea",
  "type": "dropdown",
  "label": {
    "en": "Price area"
  },
  "value": "Oslo",
  "values": [
    {
      "id": "AT",
      "label": {
        "en": "Austria - AT"
      }
    },
    {
      "id": "BE",
      "label": {
        "en": "Belgium - BE"
      }
    },
    {
      "id": "DK1",
      "label": {
        "en": "Denmark - DK1"
      }
    },
    {
      "id": "DK2",
      "label": {
        "en": "Denmark - DK2"
      }
    },
    {
      "id": "EE",
      "label": {
        "en": "Estonia - EE"
      }
    },
    {
      "id": "FI",
      "label": {
        "en": "Finland - FI"
      }
    },
    {
      "id": "FR",
      "label": {
        "en": "France - FR"
      }
    },
    {
      "id": "DE-LU",
      "label": {
        "en": "Germany and Luxembourg (DE-LU)"
      }
    },
    {
      "id": "LV",
      "label": {
        "en": "Latvia - LV"
      }
    },
    {
      "id": "LT",
      "label": {
        "en": "Lithuania - LT"
      }
    },
    {
      "id": "NL",
      "label": {
        "en": "Netherlands - NL"
      }
    },
    {
      "id": "Oslo",
      "label": {
        "en": "Norway - Oslo (NO1)"
      }
    },
    {
      "id": "Kr.sand",
      "label": {
        "en": "Norway - Kr.sand (NO2)"
      }
    },
    {
      "id": "Bergen",
      "label": {
        "en": "Norway - Bergen (NO5)"
      }
    },
    {
      "id": "Tr.heim",
      "label": {
        "en": "Norway - Tr.heim (NO3)"
      }
    },
    {
      "id": "Tromsø",
      "label": {
        "en": "Norway - Tromsø (NO4)"
      }
    },
    {
      "id": "SE1",
      "label": {
        "en": "Sweden - SE1"
      }
    },
    {
      "id": "SE2",
      "label": {
        "en": "Sweden - SE2"
      }
    },
    {
      "id": "SE3",
      "label": {
        "en": "Sweden - SE3"
      }
    },
    {
      "id": "SE4",
      "label": {
        "en": "Sweden - SE4"
      }
    }
  ]
}